LICENSE
MANIFEST.in
README.md
setup.py
pyeer/__init__.py
pyeer/cmc_info.py
pyeer/cmc_stats.py
pyeer/eer_info.py
pyeer/eer_stats.py
pyeer/plot.py
pyeer/report.py
pyeer.egg-info/PKG-INFO
pyeer.egg-info/SOURCES.txt
pyeer.egg-info/dependency_links.txt
pyeer.egg-info/entry_points.txt
pyeer.egg-info/requires.txt
pyeer.egg-info/top_level.txt
pyeer/example_files/cmc/exp1_scores.txt
pyeer/example_files/cmc/exp1_tp.txt
pyeer/example_files/cmc/exp2_scores.txt
pyeer/example_files/cmc/exp2_tp.txt
pyeer/example_files/hist/exp1_false.txt
pyeer/example_files/hist/exp1_true.txt
pyeer/example_files/non_hist/exp1_false.txt
pyeer/example_files/non_hist/exp1_true.txt
pyeer/example_files/non_hist/exp2_false.txt
pyeer/example_files/non_hist/exp2_true.txt
pyeer/example_files/non_hist/exp3_false.txt
pyeer/example_files/non_hist/exp3_true.txt