Metadata-Version: 2.1
Name: pyeer
Version: 0.5.6
Summary: A python package for biometric and binary classification systems performance evaluation
Home-page: https://github.com/manuelaguadomtz/pyeer
Author: Manuel Aguado Martínez
Author-email: manuelaguadomtz@gmail.com
Keywords: Equal Error Rate,False Match Rate,ROC,DET,False Non-Match Rate,EER,FMR,FNMR,ZeroFNMR,ZeroFMR,CMC,Biometric Systems
Classifier: Intended Audience :: Science/Research
Classifier: Operating System :: OS Independent
Classifier: Topic :: Scientific/Engineering
Classifier: Programming Language :: Python
Classifier: License :: OSI Approved :: MIT License
License-File: LICENSE
Requires-Dist: numpy
Requires-Dist: matplotlib
